odoo/addons/role_policy/README.rst
odoo/addons/role_policy/__init__.py
odoo/addons/role_policy/__manifest__.py
odoo/addons/role_policy/hooks.py
odoo/addons/role_policy/data/ir_module_category_data.xml
odoo/addons/role_policy/i18n/role_policy.pot
odoo/addons/role_policy/models/__init__.py
odoo/addons/role_policy/models/base.py
odoo/addons/role_policy/models/helpers.py
odoo/addons/role_policy/models/ir_actions.py
odoo/addons/role_policy/models/ir_http.py
odoo/addons/role_policy/models/ir_model_access.py
odoo/addons/role_policy/models/ir_ui_menu.py
odoo/addons/role_policy/models/ir_ui_view.py
odoo/addons/role_policy/models/model_method_execution_right.py
odoo/addons/role_policy/models/res_groups.py
odoo/addons/role_policy/models/res_role.py
odoo/addons/role_policy/models/res_role_acl.py
odoo/addons/role_policy/models/res_users.py
odoo/addons/role_policy/models/role_policy_menu_action_common.py
odoo/addons/role_policy/models/security_policy_tag.py
odoo/addons/role_policy/models/view_model_operation.py
odoo/addons/role_policy/models/view_modifier_rule.py
odoo/addons/role_policy/models/view_type_attribute.py
odoo/addons/role_policy/readme/CONFIGURE.rst
odoo/addons/role_policy/readme/CONTRIBUTORS.rst
odoo/addons/role_policy/readme/CREDITS.rst
odoo/addons/role_policy/readme/DESCRIPTION.rst
odoo/addons/role_policy/readme/ROADMAP.rst
odoo/addons/role_policy/report/__init__.py
odoo/addons/role_policy/report/role_policy_export_xls.py
odoo/addons/role_policy/security/ir.model.access.csv
odoo/addons/role_policy/security/role_policy_security.xml
odoo/addons/role_policy/static/description/icon.png
odoo/addons/role_policy/static/description/index.html
odoo/addons/role_policy/static/src/js/role_policy.js
odoo/addons/role_policy/views/assets_backend.xml
odoo/addons/role_policy/views/ir_actions_views.xml
odoo/addons/role_policy/views/ir_ui_menu_views.xml
odoo/addons/role_policy/views/menu.xml
odoo/addons/role_policy/views/res_groups_views.xml
odoo13_addon_role_policy-13.0.1.3.0.dist-info/METADATA
odoo13_addon_role_policy-13.0.1.3.0.dist-info/WHEEL
odoo13_addon_role_policy-13.0.1.3.0.dist-info/top_level.txt
odoo13_addon_role_policy-13.0.1.3.0.dist-info/RECORD
