Metadata-Version: 2.1
Name: odoo13-addon-role_policy
Version: 13.0.1.3.0
Summary: Role Policy
Home-page: https://github.com/OCA/role-policy
Author: Noviat, Odoo Community Association (OCA)
Author-email: support@odoo-community.org
License: AGPL-3
Classifier: Programming Language :: Python
Classifier: Framework :: Odoo
Classifier: Framework :: Odoo :: 13.0
Classifier: License :: OSI Approved :: GNU Affero General Public License v3
Requires-Python: >=3.5
Requires-Dist: lxml
Requires-Dist: odoo13-addon-report-xlsx-helper
Requires-Dist: odoo<13.1dev,>=13.0a
Requires-Dist: xlrd
